AUTHOR.txt
CHANGES.txt
COPYRIGHT.txt
LICENSE.txt
README.txt
bootstrap.py
buildout.cfg
setup.py
externals/z3c.recipe.i18n/CHANGES.txt
externals/z3c.recipe.i18n/COPYRIGHT.txt
externals/z3c.recipe.i18n/LICENSE.txt
externals/z3c.recipe.i18n/README.txt
externals/z3c.recipe.i18n/bootstrap.py
externals/z3c.recipe.i18n/buildout-zope212.cfg
externals/z3c.recipe.i18n/buildout-ztk10.cfg
externals/z3c.recipe.i18n/buildout.cfg
externals/z3c.recipe.i18n/setup.py
externals/z3c.recipe.i18n/src/z3c/__init__.py
externals/z3c.recipe.i18n/src/z3c/recipe/__init__.py
externals/z3c.recipe.i18n/src/z3c/recipe/i18n/README.txt
externals/z3c.recipe.i18n/src/z3c/recipe/i18n/__init__.py
externals/z3c.recipe.i18n/src/z3c/recipe/i18n/i18n.py
externals/z3c.recipe.i18n/src/z3c/recipe/i18n/i18ncompile.py
externals/z3c.recipe.i18n/src/z3c/recipe/i18n/i18nextract.py
externals/z3c.recipe.i18n/src/z3c/recipe/i18n/i18nmergeall.py
externals/z3c.recipe.i18n/src/z3c/recipe/i18n/i18nstats.py
externals/z3c.recipe.i18n/src/z3c/recipe/i18n/testing.zcml
externals/z3c.recipe.i18n/src/z3c/recipe/i18n/tests.py
src/zam/__init__.py
src/zam.locales.egg-info/PKG-INFO
src/zam.locales.egg-info/SOURCES.txt
src/zam.locales.egg-info/dependency_links.txt
src/zam.locales.egg-info/namespace_packages.txt
src/zam.locales.egg-info/not-zip-safe
src/zam.locales.egg-info/requires.txt
src/zam.locales.egg-info/top_level.txt
src/zam/locales/__init__.py
src/zam/locales/configure.zcml
src/zam/locales/extract.zcml
src/zam/locales/zam.pot
src/zam/locales/de/LC_MESSAGES/zam.mo
src/zam/locales/de/LC_MESSAGES/zam.po