Metadata-Version: 1.0
Name: zam.locales
Version: 0.5.0
Summary: Locales for ZAM (Zope Application Management
Home-page: http://cheeseshop.python.org/pypi/zam.locales
Author: Stephan Richter, Roger Ineichen and the Zope Community
Author-email: zope3-dev@zope.org
License: ZPL 2.1
Keywords: zope3 z3c zam locales
Platform: UNKNOWN
Classifier: Development Status :: 4 - Beta
Classifier: Environment :: Web Environment
Classifier: Intended Audience :: Developers
Classifier: License :: OSI Approved :: Zope Public License
Classifier: Programming Language :: Python
Classifier: Natural Language :: English
Classifier: Operating System :: OS Independent
Classifier: Topic :: Internet :: WWW/HTTP
Classifier: Framework :: Zope3
